pylockfile/__init__.py
pylockfile/pylockfile.py
pylockfile-0.0.3.1.dist-info/LICENSE.txt
pylockfile-0.0.3.1.dist-info/METADATA
pylockfile-0.0.3.1.dist-info/WHEEL
pylockfile-0.0.3.1.dist-info/top_level.txt
pylockfile-0.0.3.1.dist-info/RECORD
