Metadata-Version: 2.1
Name: pylockfile
Version: 0.0.3.1
Summary: Создание файла блокировки, для предотвращения выполнения нескольких копий скрипта
Home-page: https://github.com/iiiparadoxxxiii/lockfile
Author: Kusakin Anton @iiiparadoxxxiii
Author-email: iiiparadoxxxiii@gmail.com
License: UNKNOWN
Platform: UNKNOWN
